zerv/__init__.py
zerv/constants.py
zerv/exceptions.py
zerv/utils.py
zerv/cli/__init__.py
zerv/cli/deploy.py
zerv/cli/handler.py
zerv/cli/lambda_commands.py
zerv/core/__init__.py
zerv/core/main.py
zerv/deploy/__init__.py
zerv/deploy/api_gateway.py
zerv/deploy/aws_lambda.py
zerv/deploy/packager.py
zerv-0.1.0.dist-info/METADATA
zerv-0.1.0.dist-info/RECORD
zerv-0.1.0.dist-info/WHEEL
zerv-0.1.0.dist-info/entry_points.txt
zerv-0.1.0.dist-info/top_level.txt
