Metadata-Version: 2.1
Name: zerv
Version: 0.1.0
Summary: CLI Tool
Home-page: https://github.com/henocdz/zerv
Author: Henoc Díaz
Author-email: self@henocdz.com
License: GNU General Public License v3 (GPLv3)
Keywords: zerv
Platform: UNKNOWN
Classifier: Development Status :: 2 - Pre-Alpha
Classifier: Intended Audience :: Developers
Classifier: License :: OSI Approved :: GNU General Public License v3 (GPLv3)
Classifier: Topic :: Software Development :: Build Tools
Classifier: Natural Language :: English
Classifier: Programming Language :: Python :: 3.6
Requires-Dist: boto3 (<2.0.0,>=1.9.8)
Requires-Dist: botocore (<2.0.0,>=1.12.5)
Requires-Dist: chalice (<2.0.0,>=1.6.0)
Requires-Dist: click (<7.0,>=6.6)
Requires-Dist: pip (<11,>=9)
Requires-Dist: PyYAML (<4.0,>=3.13)
